{
  "timestamp": "2025-09-17T06:20:51.329316",
  "summary": {
    "added": 1,
    "removed": 0,
    "updated": 4
  },
  "details": {
    "added": [
      {
        "code": "ARTS-A0108",
        "name": "Information Literacy, Ylim\u00e4\u00e4r\u00e4inen ryhm\u00e4: arkkitehtuuri, maisema-ark. + sisustusark.",
        "credits": 1
      }
    ],
    "removed": [],
    "updated": [
      {
        "code": "CHEM-C2000",
        "name": "Course Assistant in the School of Chemical Engineering V, Lecture",
        "changes": [
          [
            "Enrolment End",
            "2025-08-31",
            "2026-06-05"
          ]
        ]
      },
      {
        "code": "CHEM-C2000001",
        "name": "Course Assistant in the School of Chemical Engineering V, Lecture",
        "changes": [
          [
            "Enrolment End",
            "2025-08-31",
            "2026-06-05"
          ]
        ]
      },
      {
        "code": "CHEM-E0125",
        "name": "Teaching Assistant Duties at the School of Chemical Engineering V, Lecture",
        "changes": [
          [
            "Enrolment End",
            "2025-08-29",
            "2026-06-05"
          ]
        ]
      },
      {
        "code": "CHEM-E0125001",
        "name": "Teaching Assistant Duties at the School of Chemical Engineering V, Lecture",
        "changes": [
          [
            "Enrolment Start",
            "2025-08-04",
            "2025-09-01"
          ],
          [
            "Enrolment End",
            "2025-08-29",
            "2026-06-05"
          ]
        ]
      }
    ]
  }
}