{
  "timestamp": "2025-07-02T06:22:11.038699",
  "summary": {
    "added": 3,
    "removed": 1,
    "updated": 6
  },
  "details": {
    "added": [
      {
        "code": "MNGT-C3002",
        "name": "Founder Insights, Lectures",
        "credits": 3
      },
      {
        "code": "MNGT-C3003",
        "name": "Founder Sprint Program, Lectures",
        "credits": 6
      },
      {
        "code": "MNGT-C3003",
        "name": "Founder Sprint Program, Lectures",
        "credits": 6
      }
    ],
    "removed": [
      {
        "code": "AAN-C2006",
        "name": "Product analysis, Lecture"
      }
    ],
    "updated": [
      {
        "code": "42E00400",
        "name": "CEMS Block Seminar, Lecture",
        "changes": [
          [
            "Enrolment End",
            "2025-08-18",
            "2025-08-11"
          ]
        ]
      },
      {
        "code": "42E00400",
        "name": "CEMS Block Seminar, Lecture",
        "changes": [
          [
            "Enrolment End",
            "2025-08-18",
            "2025-08-11"
          ]
        ]
      },
      {
        "code": "42E01200",
        "name": "CEMS Special Topics in Global Management, Lecture",
        "changes": [
          [
            "Enrolment End",
            "2025-08-25",
            "2025-09-08"
          ]
        ]
      },
      {
        "code": "37E00100",
        "name": "Information Economy, Lecture",
        "changes": [
          [
            "Enrolment End",
            "2026-03-02",
            "2026-02-22"
          ]
        ]
      },
      {
        "code": "MLI26C653",
        "name": "International Business Strategy, Lecture",
        "changes": [
          [
            "Enrolment Start",
            null,
            "2025-07-01"
          ],
          [
            "Enrolment End",
            null,
            "2026-03-15"
          ]
        ]
      },
      {
        "code": "ISM-E2004",
        "name": "Introduction to Digital Service Design, Lecture",
        "changes": [
          [
            "Enrolment End",
            "2026-01-12",
            "2026-01-08"
          ]
        ]
      }
    ]
  }
}